proadv/__init__.py
proadv/filtration/__init__.py
proadv/filtration/detection/__init__.py
proadv/filtration/detection/acceleration.py
proadv/filtration/detection/bivariatekernel.py
proadv/filtration/detection/correlation.py
proadv/filtration/detection/phasespace.py
proadv/filtration/detection/poincare.py
proadv/filtration/detection/pollution.py
proadv/filtration/detection/spherical.py
proadv/filtration/detection/trivariatekernel.py
proadv/filtration/replacement/__init__.py
proadv/filtration/replacement/replacements.py
proadv/kernel/__init__.py
proadv/kernel/bivariate.py
proadv/statistics/__init__.py
proadv/statistics/descriptive.py
proadv/statistics/moment.py
proadv/statistics/series.py
proadv/statistics/spread.py
proadv/statistics/distributions/__init__.py
proadv/statistics/distributions/normal.py
proadv/statistics/optimize/__init__.py
proadv/statistics/optimize/optimize.py
proadv/statistics/signal/__init__.py
proadv/statistics/signal/butter.py
proadv/statistics/signal/fluid.py
proadv/statistics/signal/spectrum.py
proadv/statistics/signal/synthetic.py
proadv/tests/__init__.py
proadv/tests/statistics/__init__.py
proadv/tests/statistics/descriptive/__init__.py
proadv/tests/statistics/descriptive/test_exponential_moving_average.py
proadv/tests/statistics/descriptive/test_max.py
proadv/tests/statistics/descriptive/test_mean.py
proadv/tests/statistics/descriptive/test_median.py
proadv/tests/statistics/descriptive/test_min.py
proadv/tests/statistics/descriptive/test_mode.py
proadv/tests/statistics/descriptive/test_moving_average.py
proadv-2.1.5.dist-info/METADATA
proadv-2.1.5.dist-info/WHEEL
proadv-2.1.5.dist-info/top_level.txt
proadv-2.1.5.dist-info/RECORD
