Metadata-Version: 2.1
Name: proadv
Version: 2.1.5
Summary: Process Acoustic Doppler Velocimeter data with advanced despiking and analysis tools
Home-page: https://github.com/farzadasgari/proadv
Author: Farzad Asgari
Author-email: std_farzad.asgari@alumni.khu.ac.ir
Project-URL: Download URL, https://pypi.org/project/proadv/
Project-URL: Source Code, https://github.com/farzadasgari/proadv
Project-URL: Documentation, https://proadv.readthedocs.io/en/stable/
Keywords: ProADV,python,signal processing,data processing,acoustic Doppler velocimeter,ADV,Denoising,Despiking
Classifier: Development Status :: 5 - Production/Stable
Classifier: Intended Audience :: Science/Research
Classifier: License :: OSI Approved :: MIT License
Classifier: Operating System :: OS Independent
Classifier: Programming Language :: Python :: 3
Classifier: Programming Language :: Python :: 3.8
Classifier: Programming Language :: Python :: 3.9
Classifier: Programming Language :: Python :: 3.10
Classifier: Programming Language :: Python :: 3.11
Classifier: Programming Language :: Python :: 3.12
Requires-Dist: numpy>=1.0
Requires-Dist: scipy>=1.0
Requires-Dist: scikit-learn
Requires-Dist: fastkde
